{
  "_fv": 18,
  "_type": "recipe",
  "definition": {
    "recipeType": "Crafting",
    "xpReward": 0.0,
    "cookingTime": 200,
    "recipeRetstackSize": 1,
    "group": "",
    "recipeShapeless": false,
    "recipeSlots": [
      {
        "value": "CUSTOM:Ironleaf"
      },
      {
        "value": "CUSTOM:Enchantedwood"
      },
      {
        "value": "CUSTOM:Ironleaf"
      },
      {
        "value": "CUSTOM:Enchantedwood"
      },
      {
        "value": "Items.GLOWSTONE_DUST"
      },
      {
        "value": "CUSTOM:Enchantedwood"
      },
      {
        "value": "CUSTOM:Ironleaf"
      },
      {
        "value": "CUSTOM:Enchantedwood"
      },
      {
        "value": "CUSTOM:Ironleaf"
      }
    ],
    "recipeReturnStack": {
      "value": "CUSTOM:Essencecondenser"
    },
    "name": "essencecondenserrecipe",
    "namespace": "mod"
  }
}